codeplain_REST_api.py
file_utils.py
git_utils.py
hash_key.py
plain2code.py
plain2code_arguments.py
plain2code_console.py
plain2code_exceptions.py
plain2code_nodes.py
plain2code_read_config.py
plain2code_state.py
plain2code_utils.py
plain_spec.py
system_config.py
codeplain-0.1.1.dist-info/licenses/LICENSE
config/__init__.py
config/system_config.yaml
render_machine/code_renderer.py
render_machine/conformance_test_helpers.py
render_machine/implementation_code_helpers.py
render_machine/render_context.py
render_machine/render_types.py
render_machine/render_utils.py
render_machine/state_machine_config.py
render_machine/states.py
render_machine/triggers.py
render_machine/actions/analyze_specification_ambiguity.py
render_machine/actions/base_action.py
render_machine/actions/commit_conformance_tests_changes.py
render_machine/actions/commit_implementation_code_changes.py
render_machine/actions/create_dist.py
render_machine/actions/exit_with_error.py
render_machine/actions/fix_conformance_test.py
render_machine/actions/fix_unit_tests.py
render_machine/actions/prepare_repositories.py
render_machine/actions/prepare_testing_environment.py
render_machine/actions/refactor_code.py
render_machine/actions/render_conformance_tests.py
render_machine/actions/render_functional_requirement.py
render_machine/actions/run_conformance_tests.py
render_machine/actions/run_unit_tests.py
render_machine/actions/summarize_conformance_tests.py
standard_template_library/__init__.py
standard_template_library/golang-console-app-template.plain
standard_template_library/python-console-app-template.plain
standard_template_library/typescript-react-app-template.plain
codeplain-0.1.1.dist-info/METADATA
codeplain-0.1.1.dist-info/WHEEL
codeplain-0.1.1.dist-info/entry_points.txt
codeplain-0.1.1.dist-info/top_level.txt
codeplain-0.1.1.dist-info/RECORD
