Metadata-Version: 2.4
Name: codeplain
Version: 0.1.1
Summary: Transform plain language specifications into working code
Classifier: Environment :: Console
Classifier: Intended Audience :: Developers
Classifier: License :: OSI Approved :: MIT License
Classifier: Operating System :: OS Independent
Classifier: Programming Language :: Python :: 3.11
Classifier: Topic :: Software Development :: Code Generators
Requires-Python: >=3.11
License-File: LICENSE
Requires-Dist: python-liquid2==0.3.0
Requires-Dist: mistletoe==1.3.0
Requires-Dist: langchain==1.0.8
Requires-Dist: langchain-core==1.2.3
Requires-Dist: langchain-openai==1.0.3
Requires-Dist: langchain-anthropic==1.1.0
Requires-Dist: langchain-aws==1.0.0
Requires-Dist: langchain-cerebras==0.8.0
Requires-Dist: langchain-google-genai==4.1.2
Requires-Dist: langchain-ollama==1.0.0
Requires-Dist: requests==2.32.3
Requires-Dist: langsmith==0.4.4
Requires-Dist: rich==14.2.0
Requires-Dist: tiktoken==0.12.0
Requires-Dist: PyYAML==6.0.2
Requires-Dist: gitpython==3.1.42
Requires-Dist: lizard==1.18.0
Requires-Dist: textual==1.0.0
Requires-Dist: SQLAlchemy==2.0.36
Requires-Dist: psycopg2==2.9.10
Requires-Dist: python-dotenv==1.1.0
Requires-Dist: transitions==0.9.3
Requires-Dist: cryptography==46.0.1
Provides-Extra: dev
Requires-Dist: pytest==8.3.5; extra == "dev"
Requires-Dist: flake8==7.0.0; extra == "dev"
Requires-Dist: black==24.2.0; extra == "dev"
Requires-Dist: isort==5.13.2; extra == "dev"
Requires-Dist: flake8-bugbear==24.12.12; extra == "dev"
Requires-Dist: flake8-unused-arguments==0.0.13; extra == "dev"
Requires-Dist: flake8-eradicate==1.5.0; extra == "dev"
Requires-Dist: pep8-naming==0.15.1; extra == "dev"
Requires-Dist: mypy==1.11.2; extra == "dev"
Dynamic: license-file
